LICENSE
MANIFEST.in
README.rst
setup.py
docs/Makefile
docs/changelog.rst
docs/conf.py
docs/contributing.rst
docs/forms.rst
docs/index.html
docs/index.rst
docs/license.rst
docs/modelform.html
docs/readme.rst
docs/screenshot.png
docs/settings.rst
docs/todo.rst
docs/widgets.rst
docs/_build/html/.buildinfo
docs/_build/html/architecture.html
docs/_build/html/changelog.html
docs/_build/html/contributing.html
docs/_build/html/deployment.html
docs/_build/html/forms.html
docs/_build/html/genindex.html
docs/_build/html/index.html
docs/_build/html/installation.html
docs/_build/html/license.html
docs/_build/html/objects.inv
docs/_build/html/py-modindex.html
docs/_build/html/readme.html
docs/_build/html/readme_link.html
docs/_build/html/search.html
docs/_build/html/searchindex.js
docs/_build/html/settings.html
docs/_build/html/todo.html
docs/_build/html/widgets.html
docs/_build/html/.doctrees/architecture.doctree
docs/_build/html/.doctrees/changelog.doctree
docs/_build/html/.doctrees/contributing.doctree
docs/_build/html/.doctrees/deployment.doctree
docs/_build/html/.doctrees/environment.pickle
docs/_build/html/.doctrees/forms.doctree
docs/_build/html/.doctrees/index.doctree
docs/_build/html/.doctrees/installation.doctree
docs/_build/html/.doctrees/license.doctree
docs/_build/html/.doctrees/readme.doctree
docs/_build/html/.doctrees/readme_link.doctree
docs/_build/html/.doctrees/settings.doctree
docs/_build/html/.doctrees/todo.doctree
docs/_build/html/.doctrees/widgets.doctree
docs/_build/html/_images/screenshot.png
docs/_build/html/_modules/index.html
docs/_build/html/_modules/material_widgets/forms.html
docs/_build/html/_modules/material_widgets/widgets.html
docs/_build/html/_sources/architecture.rst.txt
docs/_build/html/_sources/changelog.rst.txt
docs/_build/html/_sources/contributing.rst.txt
docs/_build/html/_sources/deployment.rst.txt
docs/_build/html/_sources/forms.rst.txt
docs/_build/html/_sources/index.rst.txt
docs/_build/html/_sources/installation.rst.txt
src/django_material_widgets.egg-info/PKG-INFO
src/django_material_widgets.egg-info/SOURCES.txt
src/django_material_widgets.egg-info/dependency_links.txt
src/django_material_widgets.egg-info/top_level.txt
