Metadata-Version: 1.1
Name: django-material-widgets
Version: 1.0.0b3
Summary: Django widgets styled with Material Components for the Web.
Home-page: https://github.com/ooknosi/django_material_widgets
Author: Edison KOO
Author-email: UNKNOWN
License: Apache Software License
Keywords: django material widgets forms modelforms
Platform: UNKNOWN
Classifier: Development Status :: 4 - Beta
Classifier: Environment :: Web Environment
Classifier: Framework :: Django
Classifier: Framework :: Django :: 1.11
Classifier: Intended Audience :: Developers
Classifier: License :: OSI Approved :: Apache Software License
Classifier: Operating System :: OS Independent
Classifier: Programming Language :: Python
Classifier: Programming Language :: Python :: 3
Classifier: Programming Language :: Python :: 3.6
Classifier: Topic :: Internet :: WWW/HTTP
Classifier: Topic :: Internet :: WWW/HTTP :: Dynamic Content
Classifier: Topic :: Software Development :: Libraries :: Python Modules
